freezeyt/__init__.py
freezeyt/__main__.py
freezeyt/actions.py
freezeyt/cli.py
freezeyt/compat.py
freezeyt/dictsaver.py
freezeyt/encoding.py
freezeyt/extra_files.py
freezeyt/filesaver.py
freezeyt/freezer.py
freezeyt/hooks.py
freezeyt/middleware.py
freezeyt/mimetype_check.py
freezeyt/plugins.py
freezeyt/saver.py
freezeyt/status_handlers.py
freezeyt/types.py
freezeyt/url_finders.py
freezeyt/urls.py
freezeyt/util.py
freezeyt-1.3.0.dist-info/licenses/LICENCE.MIT
freezeyt-1.3.0.dist-info/METADATA
freezeyt-1.3.0.dist-info/WHEEL
freezeyt-1.3.0.dist-info/entry_points.txt
freezeyt-1.3.0.dist-info/top_level.txt
freezeyt-1.3.0.dist-info/RECORD
