Metadata-Version: 2.4
Name: freezeyt
Version: 1.3.0
Summary: Generate static web pages from WSGI apps
License: MIT
Project-URL: Repository, https://github.com/encukou/freezeyt
Classifier: License :: OSI Approved :: MIT License
Classifier: Programming Language :: Python :: 3
Classifier: Programming Language :: Python :: 3.8
Classifier: Programming Language :: Python :: 3.9
Classifier: Programming Language :: Python :: 3.10
Classifier: Programming Language :: Python :: 3.11
Classifier: Programming Language :: Python :: 3.12
Classifier: Programming Language :: Python :: 3.13
Classifier: Programming Language :: Python :: 3.14
Requires-Python: >=3.8
License-File: LICENCE.MIT
Requires-Dist: html5lib
Requires-Dist: click
Requires-Dist: cssutils
Requires-Dist: pyyaml
Requires-Dist: Werkzeug
Requires-Dist: enlighten
Requires-Dist: tomli; python_version < "3.11"
Provides-Extra: dev
Requires-Dist: pytest>=6.2.0; extra == "dev"
Requires-Dist: flask; extra == "dev"
Requires-Dist: pyflakes; extra == "dev"
Requires-Dist: Django; extra == "dev"
Requires-Dist: bottle>=0.12.23; extra == "dev"
Requires-Dist: falcon; extra == "dev"
Requires-Dist: freezegun; extra == "dev"
Requires-Dist: packaging; extra == "dev"
Provides-Extra: blog
Requires-Dist: flask; extra == "blog"
Requires-Dist: markdown-it-py; extra == "blog"
Requires-Dist: pygments; extra == "blog"
Provides-Extra: typecheck
Requires-Dist: mypy; extra == "typecheck"
Requires-Dist: types-click; extra == "typecheck"
Requires-Dist: types-PyYAML; extra == "typecheck"
Requires-Dist: types-html5lib>=1.1.11.20240228; extra == "typecheck"
Dynamic: license-file
